{"round_id": "8f664aed-8839-4c85-bed0-77a2cac7c6f5", "stats": {"0": {"28,16": {"food": [0.899], "pop": [1.131], "alive": [1], "wealth": [0.157], "defense": [0.252]}, "18,17": {"food": [0.208], "pop": [2.243], "alive": [1], "wealth": [0.154], "defense": [1.0]}, "22,25": {"food": [0.786], "pop": [2.393], "alive": [1], "wealth": [0.08], "defense": [1.0]}, "21,24": {"food": [0.862], "pop": [1.54], "alive": [1], "wealth": [0.131], "defense": [0.619]}, "26,21": {"food": [0.829], "pop": [1.912], "alive": [1], "wealth": [0.036], "defense": [0.859]}, "16,29": {"food": [0.862], "pop": [1.548], "alive": [1], "wealth": [0.007], "defense": [0.528]}, "18,29": {"food": [0.898], "pop": [1.14], "alive": [1], "wealth": [0.004], "defense": [0.464]}, "26,26": {"food": [0.902], "pop": [1.092], "alive": [1], "wealth": [0.058], "defense": [0.269]}, "29,17": {"food": [0.903], "pop": [1.089], "alive": [1], "wealth": [0.048], "defense": [0.432]}, "20,23": {"food": [0.917], "pop": [0.932], "alive": [1], "wealth": [0.024], "defense": [0.38]}, "27,27": {"food": [0.763], "pop": [0.415], "alive": [1], "wealth": [0.02], "defense": [0.13]}, "19,18": {"food": [0.928], "pop": [0.81], "alive": [1], "wealth": [0.044], "defense": [0.328]}, "19,25": {"food": [0.947], "pop": [0.589], "alive": [1], "wealth": [0.061], "defense": [0.226]}, "16,28": {"food": [0.932], "pop": [0.757], "alive": [1], "wealth": [0.003], "defense": [0.311]}, "27,20": {"food": [0.928], "pop": [0.805], "alive": [1], "wealth": [0.011], "defense": [0.318]}, "27,26": {"food": [0.938], "pop": [0.689], "alive": [1], "wealth": [0.082], "defense": [0.292]}, "29,16": {"food": [0.944], "pop": [0.632], "alive": [1], "wealth": [0.05], "defense": [0.276]}, "20,25": {"food": [0.941], "pop": [0.656], "alive": [1], "wealth": [0.021], "defense": [0.279]}, "16,17": {"food": [0.939], "pop": [0.683], "alive": [1], "wealth": [0.041], "defense": [0.272]}, "20,24": {"food": [0.956], "pop": [0.488], "alive": [1], "wealth": [0.009], "defense": [0.202]}, "17,28": {"food": [0.945], "pop": [0.616], "alive": [1], "wealth": [0.003], "defense": [0.255]}, "23,24": {"food": [0.948], "pop": [0.581], "alive": [1], "wealth": [0.02], "defense": [0.233]}, "18,18": {"food": [0.488], "pop": [0.5], "alive": [1], "wealth": [0.035], "defense": [0.22]}, "25,23": {"food": [0.97], "pop": [0.335], "alive": [1], "wealth": [0.001], "defense": [0.117]}, "25,20": {"food": [0.752], "pop": [0.527], "alive": [1], "wealth": [0.01], "defense": [0.21]}, "27,22": {"food": [0.194], "pop": [0.4], "alive": [1], "wealth": [0.0], "defense": [0.15]}, "27,25": {"food": [0.039], "pop": [0.4], "alive": [1], "wealth": [0.0], "defense": [0.15]}, "11,24": {"food": [0.266, 0.505], "pop": [3.05, 0.335], "alive": [1, 1], "wealth": [0.075, 0.002], "defense": [1.0, 0.111]}, "14,20": {"food": [0.889], "pop": [0.868], "alive": [1], "wealth": [0.031], "defense": [0.354]}, "10,23": {"food": [0.967], "pop": [0.256], "alive": [1], "wealth": [0.001], "defense": [0.094]}, "9,24": {"food": [0.799], "pop": [1.575], "alive": [1], "wealth": [0.034], "defense": [0.615]}, "3,18": {"food": [0.796], "pop": [1.595], "alive": [1], "wealth": [0.033], "defense": [0.511]}, "5,17": {"food": [0.978], "pop": [0.174], "alive": [1], "wealth": [0.007], "defense": [0.053]}, "11,22": {"food": [0.939], "pop": [0.476], "alive": [1], "wealth": [0.018], "defense": [0.172]}, "10,29": {"food": [0.872], "pop": [1.004], "alive": [1], "wealth": [0.004], "defense": [0.265]}, "1,29": {"food": [0.938], "pop": [0.481], "alive": [1], "wealth": [0.001], "defense": [0.194]}, "11,17": {"food": [0.899], "pop": [0.871], "alive": [1], "wealth": [0.005], "defense": [0.2]}, "4,17": {"food": [0.938], "pop": [0.482], "alive": [1], "wealth": [0.002], "defense": [0.186]}, "9,17": {"food": [0.18], "pop": [0.4], "alive": [1], "wealth": [0.001], "defense": [0.15]}, "18,5": {"food": [0.531], "pop": [2.22], "alive": [1], "wealth": [0.075], "defense": [1.0]}, "19,7": {"food": [0.635], "pop": [1.311], "alive": [1], "wealth": [0.021], "defense": [0.591]}, "29,3": {"food": [0.831], "pop": [1.474], "alive": [1], "wealth": [0.013], "defense": [0.503]}, "19,5": {"food": [0.9], "pop": [0.878], "alive": [1], "wealth": [0.022], "defense": [0.361]}, "20,6": {"food": [0.922], "pop": [0.678], "alive": [1], "wealth": [0.002], "defense": [0.276]}, "20,5": {"food": [0.175], "pop": [0.4], "alive": [1], "wealth": [0.002], "defense": [0.158]}, "16,3": {"food": [0.394], "pop": [0.32], "alive": [1], "wealth": [0.002], "defense": [0.111]}, "18,3": {"food": [0.266], "pop": [0.5], "alive": [1], "wealth": [0.021], "defense": [0.2]}, "18,8": {"food": [0.158], "pop": [0.5], "alive": [1], "wealth": [0.005], "defense": [0.2]}, "7,13": {"food": [0.124], "pop": [2.135], "alive": [1], "wealth": [0.014], "defense": [1.0]}, "5,13": {"food": [0.383], "pop": [1.51], "alive": [1], "wealth": [0.022], "defense": [0.768]}, "12,3": {"food": [0.458], "pop": [2.194], "alive": [1], "wealth": [0.014], "defense": [0.786]}, "6,11": {"food": [0.576], "pop": [1.759], "alive": [1], "wealth": [0.02], "defense": [0.761]}, "6,10": {"food": [0.603], "pop": [1.385], "alive": [1], "wealth": [0.004], "defense": [0.658]}, "14,3": {"food": [0.569], "pop": [1.725], "alive": [1], "wealth": [0.025], "defense": [0.813]}, "5,14": {"food": [0.817], "pop": [1.465], "alive": [1], "wealth": [0.091], "defense": [0.607]}, "12,2": {"food": [0.811], "pop": [1.507], "alive": [1], "wealth": [0.014], "defense": [0.616]}, "14,2": {"food": [0.853], "pop": [1.176], "alive": [1], "wealth": [0.003], "defense": [0.48]}, "7,6": {"food": [0.847], "pop": [1.224], "alive": [1], "wealth": [0.002], "defense": [0.44]}, "8,12": {"food": [0.887], "pop": [0.9], "alive": [1], "wealth": [0.002], "defense": [0.371]}, "7,14": {"food": [0.953], "pop": [0.379], "alive": [1], "wealth": [0.001], "defense": [0.13]}, "11,4": {"food": [0.887], "pop": [0.906], "alive": [1], "wealth": [0.016], "defense": [0.374]}, "6,13": {"food": [0.475], "pop": [0.5], "alive": [1], "wealth": [0.004], "defense": [0.26]}, "5,10": {"food": [0.83], "pop": [0.552], "alive": [1], "wealth": [0.005], "defense": [0.231]}, "9,13": {"food": [0.931], "pop": [0.55], "alive": [1], "wealth": [0.006], "defense": [0.221]}, "12,4": {"food": [0.567], "pop": [0.42], "alive": [1], "wealth": [0.003], "defense": [0.166]}, "13,4": {"food": [0.945], "pop": [0.438], "alive": [1], "wealth": [0.002], "defense": [0.167]}, "6,12": {"food": [0.451], "pop": [0.4], "alive": [1], "wealth": [0.002], "defense": [0.166]}, "5,11": {"food": [0.094], "pop": [0.5], "alive": [1], "wealth": [0.005], "defense": [0.2]}, "14,4": {"food": [0.153], "pop": [0.5], "alive": [1], "wealth": [0.006], "defense": [0.2]}, "22,31": {"food": [0.533], "pop": [3.224], "alive": [1], "wealth": [0.076], "defense": [1.0]}, "25,34": {"food": [0.398], "pop": [2.863], "alive": [1], "wealth": [0.053], "defense": [1.0]}, "28,32": {"food": [0.326], "pop": [2.027], "alive": [1], "wealth": [0.008], "defense": [1.0]}, "19,37": {"food": [0.25], "pop": [2.506], "alive": [1], "wealth": [0.121], "defense": [1.0]}, "18,35": {"food": [0.484], "pop": [1.632], "alive": [1], "wealth": [0.071], "defense": [0.817]}, "28,35": {"food": [0.841], "pop": [1.604], "alive": [1], "wealth": [0.022], "defense": [0.638]}, "28,33": {"food": [0.92], "pop": [0.813], "alive": [1], "wealth": [0.008], "defense": [0.332]}, "27,35": {"food": [0.899], "pop": [1.021], "alive": [1], "wealth": [0.017], "defense": [0.415]}, "19,36": {"food": [0.899], "pop": [1.022], "alive": [1], "wealth": [0.031], "defense": [0.419]}, "27,32": {"food": [0.918], "pop": [0.834], "alive": [1], "wealth": [0.003], "defense": [0.343]}, "20,38": {"food": [0.915], "pop": [0.863], "alive": [1], "wealth": [0.037], "defense": [0.349]}, "20,37": {"food": [0.933], "pop": [0.681], "alive": [1], "wealth": [0.025], "defense": [0.282]}, "26,33": {"food": [0.939], "pop": [0.614], "alive": [1], "wealth": [0.014], "defense": [0.255]}, "27,34": {"food": [0.952], "pop": [0.486], "alive": [1], "wealth": [0.003], "defense": [0.194]}, "20,35": {"food": [0.972], "pop": [0.279], "alive": [1], "wealth": [0.003], "defense": [0.097]}, "18,36": {"food": [0.643], "pop": [0.443], "alive": [1], "wealth": [0.0], "defense": [0.191]}, "18,34": {"food": [0.942], "pop": [0.584], "alive": [1], "wealth": [0.019], "defense": [0.243]}, "20,31": {"food": [0.772], "pop": [0.279], "alive": [1], "wealth": [0.002], "defense": [0.087]}, "17,37": {"food": [0.596], "pop": [0.419], "alive": [1], "wealth": [0.003], "defense": [0.166]}, "24,33": {"food": [0.365], "pop": [0.425], "alive": [1], "wealth": [0.012], "defense": [0.168]}, "17,35": {"food": [0.127], "pop": [0.5], "alive": [1], "wealth": [0.016], "defense": [0.2]}, "36,12": {"food": [0.815], "pop": [1.292], "alive": [1], "wealth": [0.001], "defense": [0.328]}, "36,10": {"food": [0.908], "pop": [0.644], "alive": [1], "wealth": [0.005], "defense": [0.254]}, "35,12": {"food": [0.958], "pop": [0.294], "alive": [1], "wealth": [0.01], "defense": [0.096]}, "30,29": {"food": [0.855], "pop": [1.872], "alive": [1], "wealth": [0.074], "defense": [0.728]}, "31,23": {"food": [0.539], "pop": [2.655], "alive": [1], "wealth": [0.058], "defense": [1.0]}, "30,16": {"food": [0.367], "pop": [2.108], "alive": [1], "wealth": [0.06], "defense": [0.841]}, "32,28": {"food": [0.943], "pop": [0.735], "alive": [1], "wealth": [0.04], "defense": [0.317]}, "34,28": {"food": [0.952], "pop": [0.616], "alive": [1], "wealth": [0.004], "defense": [0.25]}, "31,26": {"food": [0.78], "pop": [0.293], "alive": [1], "wealth": [0.005], "defense": [0.083]}, "32,27": {"food": [0.96], "pop": [0.514], "alive": [1], "wealth": [0.01], "defense": [0.203]}, "30,22": {"food": [0.984], "pop": [0.206], "alive": [1], "wealth": [0.001], "defense": [0.061]}, "32,29": {"food": [0.963], "pop": [0.482], "alive": [1], "wealth": [0.008], "defense": [0.194]}, "30,15": {"food": [0.964], "pop": [0.463], "alive": [1], "wealth": [0.003], "defense": [0.184]}, "31,18": {"food": [0.964], "pop": [0.459], "alive": [1], "wealth": [0.0], "defense": [0.184]}, "30,27": {"food": [0.957], "pop": [0.55], "alive": [1], "wealth": [0.019], "defense": [0.221]}, "32,22": {"food": [0.63], "pop": [0.527], "alive": [1], "wealth": [0.015], "defense": [0.21]}, "31,16": {"food": [0.106], "pop": [0.5], "alive": [1], "wealth": [0.014], "defense": [0.2]}, "4,36": {"food": [0.462, 0.954], "pop": [2.447, 0.587], "alive": [1, 1], "wealth": [0.0, 0.001], "defense": [1.0, 0.237]}, "12,35": {"food": [0.721], "pop": [2.053], "alive": [1], "wealth": [0.053], "defense": [0.823]}, "6,31": {"food": [0.734], "pop": [1.709], "alive": [1], "wealth": [0.002], "defense": [0.59]}, "1,37": {"food": [0.838], "pop": [1.192], "alive": [1], "wealth": [0.007], "defense": [0.487]}, "5,37": {"food": [0.863, 0.176], "pop": [1.005, 0.5], "alive": [1, 1], "wealth": [0.006, 0.004], "defense": [0.406, 0.2]}, "14,35": {"food": [0.942], "pop": [0.429], "alive": [1], "wealth": [0.002], "defense": [0.157]}, "6,36": {"food": [0.9], "pop": [0.732], "alive": [1], "wealth": [0.0], "defense": [0.299]}, "4,31": {"food": [0.877], "pop": [0.905], "alive": [1], "wealth": [0.0], "defense": [0.292]}, "2,30": {"food": [0.419], "pop": [0.4], "alive": [1], "wealth": [0.0], "defense": [0.158]}, "3,31": {"food": [0.315], "pop": [0.4], "alive": [1], "wealth": [0.0], "defense": [0.158]}, "2,36": {"food": [0.473], "pop": [0.4], "alive": [1], "wealth": [0.0], "defense": [0.158]}, "2,31": {"food": [0.253], "pop": [0.4], "alive": [1], "wealth": [0.0], "defense": [0.158]}, "8,32": {"food": [0.147, 0.951], "pop": [0.4, 0.62], "alive": [1, 1], "wealth": [0.0, 0.012], "defense": [0.15, 0.256]}, "7,30": {"food": [0.029], "pop": [0.4], "alive": [1], "wealth": [0.0], "defense": [0.15]}, "35,33": {"food": [0.076], "pop": [2.686], "alive": [1], "wealth": [0.012], "defense": [1.0]}, "36,36": {"food": [0.804], "pop": [2.281], "alive": [1], "wealth": [0.014], "defense": [1.0]}, "35,32": {"food": [0.929], "pop": [0.825], "alive": [1], "wealth": [0.004], "defense": [0.33]}, "36,38": {"food": [0.929], "pop": [0.825], "alive": [1], "wealth": [0.004], "defense": [0.33]}, "36,32": {"food": [0.943], "pop": [0.662], "alive": [1], "wealth": [0.003], "defense": [0.269]}, "35,35": {"food": [0.941], "pop": [0.692], "alive": [1], "wealth": [0.004], "defense": [0.272]}, "34,33": {"food": [0.8], "pop": [0.529], "alive": [1], "wealth": [0.003], "defense": [0.22]}, "35,37": {"food": [0.931], "pop": [0.557], "alive": [1], "wealth": [0.003], "defense": [0.222]}, "2,23": {"food": [0.279], "pop": [3.157], "alive": [1], "wealth": [0.034], "defense": [1.0]}, "13,37": {"food": [0.137], "pop": [1.879], "alive": [1], "wealth": [0.028], "defense": [0.932]}, "14,37": {"food": [0.352], "pop": [1.839], "alive": [1], "wealth": [0.065], "defense": [0.924]}, "5,36": {"food": [0.641], "pop": [1.827], "alive": [1], "wealth": [0.018], "defense": [0.666]}, "7,31": {"food": [0.711], "pop": [1.676], "alive": [1], "wealth": [0.047], "defense": [0.736]}, "10,27": {"food": [0.633], "pop": [1.925], "alive": [1], "wealth": [0.051], "defense": [0.85]}, "6,23": {"food": [0.894], "pop": [1.344], "alive": [1], "wealth": [0.051], "defense": [0.54]}, "8,31": {"food": [0.79], "pop": [1.671], "alive": [1], "wealth": [0.057], "defense": [0.668]}, "5,31": {"food": [0.931], "pop": [0.871], "alive": [1], "wealth": [0.03], "defense": [0.315]}, "4,25": {"food": [0.928], "pop": [0.908], "alive": [1], "wealth": [0.015], "defense": [0.372]}, "10,26": {"food": [0.933], "pop": [0.852], "alive": [1], "wealth": [0.0], "defense": [0.324]}, "1,24": {"food": [0.938], "pop": [0.784], "alive": [1], "wealth": [0.006], "defense": [0.321]}, "2,37": {"food": [0.921], "pop": [1.005], "alive": [1], "wealth": [0.006], "defense": [0.406]}, "13,23": {"food": [0.935], "pop": [0.829], "alive": [1], "wealth": [0.043], "defense": [0.282]}, "12,36": {"food": [0.952], "pop": [0.611], "alive": [1], "wealth": [0.008], "defense": [0.249]}, "11,28": {"food": [0.951], "pop": [0.621], "alive": [1], "wealth": [0.014], "defense": [0.246]}, "13,35": {"food": [0.954], "pop": [0.577], "alive": [1], "wealth": [0.006], "defense": [0.233]}, "12,37": {"food": [0.246], "pop": [0.4], "alive": [1], "wealth": [0.001], "defense": [0.166]}, "6,30": {"food": [0.502], "pop": [0.5], "alive": [1], "wealth": [0.011], "defense": [0.21]}, "4,37": {"food": [0.408], "pop": [0.4], "alive": [1], "wealth": [0.002], "defense": [0.158]}, "12,27": {"food": [0.308], "pop": [0.5], "alive": [1], "wealth": [0.014], "defense": [0.2]}}, "1": {"20,16": {"food": [0.575], "pop": [2.084], "alive": [1], "wealth": [0.01], "defense": [0.924]}, "27,29": {"food": [0.816], "pop": [2.205], "alive": [1], "wealth": [0.032], "defense": [1.0]}, "18,17": {"food": [0.058], "pop": [1.814], "alive": [1], "wealth": [0.017], "defense": [1.0]}, "26,24": {"food": [0.58], "pop": [2.389], "alive": [1], "wealth": [0.043], "defense": [0.927]}, "19,17": {"food": [0.501], "pop": [1.553], "alive": [1], "wealth": [0.019], "defense": [0.828]}, "18,24": {"food": [0.876], "pop": [1.358], "alive": [1], "wealth": [0.002], "defense": [0.507]}, "29,22": {"food": [0.865], "pop": [1.616], "alive": [1], "wealth": [0.011], "defense": [0.583]}, "24,24": {"food": [0.887], "pop": [1.352], "alive": [1], "wealth": [0.005], "defense": [0.546]}, "25,15": {"food": [0.862], "pop": [1.652], "alive": [1], "wealth": [0.007], "defense": [0.527]}, "16,20": {"food": [0.881], "pop": [1.431], "alive": [1], "wealth": [0.06], "defense": [0.574]}, "17,25": {"food": [0.907], "pop": [1.108], "alive": [1], "wealth": [0.007], "defense": [0.455]}, "16,27": {"food": [0.886], "pop": [1.36], "alive": [1], "wealth": [0.018], "defense": [0.534]}, "23,27": {"food": [0.919], "pop": [0.973], "alive": [1], "wealth": [0.003], "defense": [0.35]}, "15,26": {"food": [0.908], "pop": [1.103], "alive": [1], "wealth": [0.015], "defense": [0.434]}, "24,26": {"food": [0.918], "pop": [0.987], "alive": [1], "wealth": [0.008], "defense": [0.39]}, "26,17": {"food": [0.92], "pop": [0.953], "alive": [1], "wealth": [0.017], "defense": [0.386]}, "24,17": {"food": [0.968], "pop": [0.385], "alive": [1], "wealth": [0.016], "defense": [0.147]}, "29,29": {"food": [0.928], "pop": [0.858], "alive": [1], "wealth": [0.005], "defense": [0.349]}, "19,16": {"food": [0.869, 0.137], "pop": [0.788, 0.4], "alive": [1, 1], "wealth": [0.005, 0.002], "defense": [0.326, 0.15]}, "25,25": {"food": [0.933], "pop": [0.801], "alive": [1], "wealth": [0.011], "defense": [0.317]}, "19,15": {"food": [0.941], "pop": [0.707], "alive": [1], "wealth": [0.003], "defense": [0.295]}, "27,17": {"food": [0.959], "pop": [0.486], "alive": [1], "wealth": [0.011], "defense": [0.19]}, "17,17": {"food": [0.967, 0.913], "pop": [0.39, 0.618], "alive": [1, 1], "wealth": [0.004, 0.004], "defense": [0.139, 0.265]}, "26,25": {"food": [0.957], "pop": [0.515], "alive": [1], "wealth": [0.018], "defense": [0.193]}, "17,23": {"food": [0.963], "pop": [0.441], "alive": [1], "wealth": [0.004], "defense": [0.167]}, "20,18": {"food": [0.949], "pop": [0.613], "alive": [1], "wealth": [0.004], "defense": [0.255]}, "18,16": {"food": [0.952], "pop": [0.58], "alive": [1], "wealth": [0.002], "defense": [0.243]}, "21,19": {"food": [0.962], "pop": [0.458], "alive": [1], "wealth": [0.0], "defense": [0.176]}, "18,25": {"food": [0.604], "pop": [0.421], "alive": [1], "wealth": [0.002], "defense": [0.174]}, "25,18": {"food": [0.566], "pop": [0.419], "alive": [1], "wealth": [0.006], "defense": [0.166]}, "18,22": {"food": [0.495], "pop": [0.5], "alive": [1], "wealth": [0.001], "defense": [0.21]}, "17,21": {"food": [0.606], "pop": [0.526], "alive": [1], "wealth": [0.014], "defense": [0.21]}, "26,16": {"food": [0.535], "pop": [0.418], "alive": [1], "wealth": [0.001], "defense": [0.158]}, "25,24": {"food": [0.26], "pop": [0.4], "alive": [1], "wealth": [0.002], "defense": [0.158]}, "25,20": {"food": [0.392], "pop": [0.4], "alive": [1], "wealth": [0.006], "defense": [0.158]}, "17,18": {"food": [0.479], "pop": [0.4], "alive": [1], "wealth": [0.0], "defense": [0.158]}, "25,23": {"food": [0.392], "pop": [0.4], "alive": [1], "wealth": [0.0], "defense": [0.158]}, "3,21": {"food": [0.164], "pop": [2.627], "alive": [1], "wealth": [0.056], "defense": [1.0]}, "7,28": {"food": [0.027], "pop": [3.114], "alive": [1], "wealth": [0.014], "defense": [1.0]}, "5,20": {"food": [0.613], "pop": [2.257], "alive": [1], "wealth": [0.056], "defense": [1.0]}, "10,22": {"food": [0.109], "pop": [2.18], "alive": [1], "wealth": [0.076], "defense": [0.925]}, "12,15": {"food": [0.817, 0.922], "pop": [1.639, 0.552], "alive": [1, 1], "wealth": [0.007, 0.003], "defense": [0.705, 0.217]}, "4,18": {"food": [0.165], "pop": [1.834], "alive": [1], "wealth": [0.011], "defense": [0.662]}, "5,18": {"food": [0.856, 0.749], "pop": [1.292, 1.781], "alive": [1, 1], "wealth": [0.01, 0.084], "defense": [0.534, 0.543]}, "2,22": {"food": [0.869], "pop": [1.175], "alive": [1], "wealth": [0.023], "defense": [0.474]}, "4,15": {"food": [0.911], "pop": [0.802], "alive": [1], "wealth": [0.004], "defense": [0.326]}, "7,27": {"food": [0.897], "pop": [0.924], "alive": [1], "wealth": [0.004], "defense": [0.379]}, "9,24": {"food": [0.878], "pop": [1.092], "alive": [1], "wealth": [0.023], "defense": [0.396]}, "10,23": {"food": [0.936], "pop": [0.572], "alive": [1], "wealth": [0.004], "defense": [0.243]}, "3,18": {"food": [0.932], "pop": [0.612], "alive": [1], "wealth": [0.001], "defense": [0.249]}, "14,22": {"food": [0.968], "pop": [0.286], "alive": [1], "wealth": [0.012], "defense": [0.096]}, "3,19": {"food": [0.916], "pop": [0.757], "alive": [1], "wealth": [0.017], "defense": [0.311]}, "3,16": {"food": [0.918], "pop": [0.737], "alive": [1], "wealth": [0.006], "defense": [0.3]}, "4,21": {"food": [0.928], "pop": [0.649], "alive": [1], "wealth": [0.015], "defense": [0.268]}, "1,21": {"food": [0.928], "pop": [0.642], "alive": [1], "wealth": [0.015], "defense": [0.258]}, "4,16": {"food": [0.784], "pop": [0.555], "alive": [1], "wealth": [0.006], "defense": [0.241]}, "9,23": {"food": [0.942], "pop": [0.46], "alive": [1], "wealth": [0.0], "defense": [0.184]}, "4,19": {"food": [0.524], "pop": [0.527], "alive": [1], "wealth": [0.013], "defense": [0.22]}, "10,15": {"food": [0.649], "pop": [0.525], "alive": [1], "wealth": [0.002], "defense": [0.21]}, "4,29": {"food": [0.509], "pop": [0.525], "alive": [1], "wealth": [0.011], "defense": [0.21]}, "1,29": {"food": [0.061], "pop": [0.4], "alive": [1], "wealth": [0.0], "defense": [0.15]}, "22,3": {"food": [0.843], "pop": [1.643], "alive": [1], "wealth": [0.015], "defense": [0.505]}, "24,5": {"food": [0.882], "pop": [1.232], "alive": [1], "wealth": [0.025], "defense": [0.482]}, "23,2": {"food": [0.936], "pop": [0.669], "alive": [1], "wealth": [0.001], "defense": [0.267]}, "23,4": {"food": [0.937], "pop": [0.658], "alive": [1], "wealth": [0.01], "defense": [0.264]}, "29,13": {"food": [0.94], "pop": [0.63], "alive": [1], "wealth": [0.0], "defense": [0.253]}, "24,2": {"food": [0.929], "pop": [0.746], "alive": [1], "wealth": [0.019], "defense": [0.308]}, "24,3": {"food": [0.949], "pop": [0.532], "alive": [1], "wealth": [0.002], "defense": [0.207]}, "28,14": {"food": [0.167], "pop": [0.5], "alive": [1], "wealth": [0.015], "defense": [0.2]}, "11,13": {"food": [0.05, 0.796], "pop": [3.215, 1.446], "alive": [1, 1], "wealth": [0.045, 0.028], "defense": [1.0, 0.522]}, "8,1": {"food": [0.028], "pop": [2.277], "alive": [1], "wealth": [0.034], "defense": [1.0]}, "13,11": {"food": [0.643, 0.855], "pop": [1.912, 1.03], "alive": [1, 1], "wealth": [0.039, 0.006], "defense": [0.889, 0.416]}, "8,3": {"food": [0.798], "pop": [1.48], "alive": [1], "wealth": [0.004], "defense": [0.681]}, "10,12": {"food": [0.761], "pop": [1.746], "alive": [1], "wealth": [0.039], "defense": [0.756]}, "11,9": {"food": [0.771, 0.917], "pop": [1.678, 0.587], "alive": [1, 1], "wealth": [0.024, 0.017], "defense": [0.658, 0.233]}, "2,9": {"food": [0.561], "pop": [1.711], "alive": [1], "wealth": [0.035], "defense": [0.593]}, "14,12": {"food": [0.81], "pop": [1.391], "alive": [1], "wealth": [0.044], "defense": [0.55]}, "1,7": {"food": [0.839], "pop": [1.179], "alive": [1], "wealth": [0.035], "defense": [0.446]}, "13,13": {"food": [0.857], "pop": [1.047], "alive": [1], "wealth": [0.016], "defense": [0.412]}, "12,12": {"food": [0.906, 0.614], "pop": [0.69, 0.527], "alive": [1, 1], "wealth": [0.002, 0.003], "defense": [0.277, 0.22]}, "1,8": {"food": [0.91], "pop": [0.66], "alive": [1], "wealth": [0.004], "defense": [0.264]}, "12,14": {"food": [0.884], "pop": [0.849], "alive": [1], "wealth": [0.014], "defense": [0.335]}, "11,11": {"food": [0.919], "pop": [0.594], "alive": [1], "wealth": [0.002], "defense": [0.238]}, "13,14": {"food": [0.906], "pop": [0.69], "alive": [1], "wealth": [0.004], "defense": [0.292]}, "4,8": {"food": [0.899], "pop": [0.74], "alive": [1], "wealth": [0.012], "defense": [0.298]}, "12,10": {"food": [0.911, 0.403], "pop": [0.652, 2.416], "alive": [1, 1], "wealth": [0.01, 0.074], "defense": [0.259, 1.0]}, "3,8": {"food": [0.937], "pop": [0.459], "alive": [1], "wealth": [0.0], "defense": [0.176]}, "7,1": {"food": [0.733], "pop": [0.439], "alive": [1], "wealth": [0.001], "defense": [0.175]}, "10,13": {"food": [0.46], "pop": [0.5], "alive": [1], "wealth": [0.01], "defense": [0.22]}, "10,3": {"food": [0.855], "pop": [0.526], "alive": [1], "wealth": [0.001], "defense": [0.22]}, "8,12": {"food": [0.924], "pop": [0.556], "alive": [1], "wealth": [0.009], "defense": [0.222]}, "25,36": {"food": [0.702], "pop": [1.743], "alive": [1], "wealth": [0.019], "defense": [0.641]}, "24,36": {"food": [0.828], "pop": [1.272], "alive": [1], "wealth": [0.033], "defense": [0.499]}, "25,35": {"food": [0.894], "pop": [0.789], "alive": [1], "wealth": [0.002], "defense": [0.321]}, "15,30": {"food": [0.893], "pop": [0.796], "alive": [1], "wealth": [0.012], "defense": [0.322]}, "29,31": {"food": [0.881], "pop": [0.878], "alive": [1], "wealth": [0.013], "defense": [0.217]}, "26,31": {"food": [0.912], "pop": [0.651], "alive": [1], "wealth": [0.006], "defense": [0.263]}, "28,31": {"food": [0.92], "pop": [0.59], "alive": [1], "wealth": [0.057], "defense": [0.238]}, "29,30": {"food": [0.92], "pop": [0.591], "alive": [1], "wealth": [0.028], "defense": [0.253]}, "33,7": {"food": [0.549], "pop": [2.175], "alive": [1], "wealth": [0.034], "defense": [0.984]}, "34,2": {"food": [0.01], "pop": [2.347], "alive": [1], "wealth": [0.027], "defense": [0.895]}, "34,1": {"food": [0.822], "pop": [1.575], "alive": [1], "wealth": [0.027], "defense": [0.719]}, "32,6": {"food": [0.613], "pop": [1.528], "alive": [1], "wealth": [0.034], "defense": [0.684]}, "35,2": {"food": [0.835], "pop": [1.463], "alive": [1], "wealth": [0.027], "defense": [0.595]}, "32,5": {"food": [0.874], "pop": [1.115], "alive": [1], "wealth": [0.03], "defense": [0.446]}, "37,12": {"food": [0.883], "pop": [1.04], "alive": [1], "wealth": [0.014], "defense": [0.411]}, "37,14": {"food": [0.922], "pop": [0.691], "alive": [1], "wealth": [0.0], "defense": [0.28]}, "36,4": {"food": [0.9], "pop": [0.888], "alive": [1], "wealth": [0.012], "defense": [0.352]}, "33,5": {"food": [0.914], "pop": [0.76], "alive": [1], "wealth": [0.01], "defense": [0.301]}, "34,6": {"food": [0.919], "pop": [0.721], "alive": [1], "wealth": [0.01], "defense": [0.286]}, "32,2": {"food": [0.928], "pop": [0.641], "alive": [1], "wealth": [0.007], "defense": [0.258]}, "34,4": {"food": [0.675], "pop": [0.419], "alive": [1], "wealth": [0.003], "defense": [0.166]}, "34,8": {"food": [0.939], "pop": [0.439], "alive": [1], "wealth": [0.004], "defense": [0.167]}, "35,3": {"food": [0.528], "pop": [0.419], "alive": [1], "wealth": [0.003], "defense": [0.166]}, "33,2": {"food": [0.312], "pop": [0.5], "alive": [1], "wealth": [0.006], "defense": [0.21]}, "34,3": {"food": [0.315], "pop": [0.5], "alive": [1], "wealth": [0.006], "defense": [0.21]}, "30,6": {"food": [0.167], "pop": [0.425], "alive": [1], "wealth": [0.008], "defense": [0.16]}, "12,34": {"food": [0.061], "pop": [4.599], "alive": [1], "wealth": [0.144], "defense": [1.0]}, "2,31": {"food": [0.599], "pop": [1.483], "alive": [1], "wealth": [0.007], "defense": [0.572]}, "13,35": {"food": [0.905], "pop": [1.095], "alive": [1], "wealth": [0.012], "defense": [0.444]}, "3,31": {"food": [0.913], "pop": [1.004], "alive": [1], "wealth": [0.007], "defense": [0.411]}, "1,34": {"food": [0.888], "pop": [1.293], "alive": [1], "wealth": [0.014], "defense": [0.523]}, "11,35": {"food": [0.897], "pop": [1.191], "alive": [1], "wealth": [0.062], "defense": [0.476]}, "9,31": {"food": [0.903], "pop": [1.12], "alive": [1], "wealth": [0.067], "defense": [0.436]}, "3,32": {"food": [0.911], "pop": [1.025], "alive": [1], "wealth": [0.012], "defense": [0.419]}, "13,33": {"food": [0.934], "pop": [0.756], "alive": [1], "wealth": [0.029], "defense": [0.295]}, "13,37": {"food": [0.916], "pop": [0.971], "alive": [1], "wealth": [0.015], "defense": [0.388]}, "10,36": {"food": [0.95], "pop": [0.582], "alive": [1], "wealth": [0.006], "defense": [0.229]}, "10,30": {"food": [0.952], "pop": [0.549], "alive": [1], "wealth": [0.036], "defense": [0.217]}, "1,30": {"food": [0.868], "pop": [0.492], "alive": [1], "wealth": [0.005], "defense": [0.21]}, "11,36": {"food": [0.721], "pop": [0.562], "alive": [1], "wealth": [0.011], "defense": [0.252]}, "1,32": {"food": [0.958], "pop": [0.484], "alive": [1], "wealth": [0.001], "defense": [0.194]}, "11,31": {"food": [0.778], "pop": [0.257], "alive": [1], "wealth": [0.0], "defense": [0.078]}, "12,32": {"food": [0.971], "pop": [0.334], "alive": [1], "wealth": [0.001], "defense": [0.117]}, "2,32": {"food": [0.156], "pop": [0.5], "alive": [1], "wealth": [0.002], "defense": [0.2]}, "12,36": {"food": [0.012], "pop": [0.4], "alive": [1], "wealth": [0.014], "defense": [0.15]}, "1,31": {"food": [0.178], "pop": [0.4], "alive": [1], "wealth": [0.001], "defense": [0.15]}, "11,33": {"food": [0.194], "pop": [0.4], "alive": [1], "wealth": [0.0], "defense": [0.15]}, "13,34": {"food": [0.039], "pop": [0.4], "alive": [1], "wealth": [0.0], "defense": [0.15]}, "13,36": {"food": [0.19], "pop": [0.4], "alive": [1], "wealth": [0.001], "defense": [0.15]}, "31,15": {"food": [0.676], "pop": [2.26], "alive": [1], "wealth": [0.077], "defense": [0.886]}, "33,19": {"food": [0.255], "pop": [1.9], "alive": [1], "wealth": [0.042], "defense": [0.801]}, "30,23": {"food": [0.811], "pop": [1.585], "alive": [1], "wealth": [0.006], "defense": [0.573]}, "32,19": {"food": [0.801], "pop": [1.558], "alive": [1], "wealth": [0.048], "defense": [0.612]}, "30,25": {"food": [0.804], "pop": [1.532], "alive": [1], "wealth": [0.011], "defense": [0.614]}, "33,18": {"food": [0.897], "pop": [0.804], "alive": [1], "wealth": [0.005], "defense": [0.323]}, "34,21": {"food": [0.904], "pop": [0.752], "alive": [1], "wealth": [0.01], "defense": [0.306]}, "35,19": {"food": [0.916], "pop": [0.661], "alive": [1], "wealth": [0.011], "defense": [0.269]}, "34,18": {"food": [0.46], "pop": [0.4], "alive": [1], "wealth": [0.005], "defense": [0.158]}, "31,17": {"food": [0.179], "pop": [0.4], "alive": [1], "wealth": [0.0], "defense": [0.15]}, "30,35": {"food": [0.026], "pop": [2.929], "alive": [1], "wealth": [0.196], "defense": [1.0]}, "31,35": {"food": [0.555], "pop": [1.7], "alive": [1], "wealth": [0.059], "defense": [0.831]}, "30,37": {"food": [0.903], "pop": [0.715], "alive": [1], "wealth": [0.045], "defense": [0.286]}, "30,33": {"food": [0.931], "pop": [0.509], "alive": [1], "wealth": [0.02], "defense": [0.204]}, "33,35": {"food": [0.917], "pop": [0.613], "alive": [1], "wealth": [0.016], "defense": [0.245]}, "13,12": {"food": [0.702], "pop": [1.575], "alive": [1], "wealth": [0.011], "defense": [0.712]}, "17,16": {"food": [0.789], "pop": [1.5], "alive": [1], "wealth": [0.003], "defense": [0.465]}, "18,19": {"food": [0.866], "pop": [0.952], "alive": [1], "wealth": [0.03], "defense": [0.365]}, "6,17": {"food": [0.884], "pop": [0.82], "alive": [1], "wealth": [0.038], "defense": [0.313]}, "18,15": {"food": [0.897], "pop": [0.731], "alive": [1], "wealth": [0.003], "defense": [0.295]}, "18,18": {"food": [0.93], "pop": [0.495], "alive": [1], "wealth": [0.002], "defense": [0.218]}, "13,10": {"food": [0.902], "pop": [0.696], "alive": [1], "wealth": [0.019], "defense": [0.283]}, "8,5": {"food": [0.145], "pop": [0.5], "alive": [1], "wealth": [0.008], "defense": [0.2]}}, "2": {"24,26": {"food": [0.575], "pop": [3.268], "alive": [1], "wealth": [0.04], "defense": [1.0]}, "23,24": {"food": [0.705], "pop": [2.268], "alive": [1], "wealth": [0.033], "defense": [1.0]}, "19,29": {"food": [0.194], "pop": [3.192], "alive": [1], "wealth": [0.047], "defense": [1.0]}, "18,20": {"food": [0.814], "pop": [1.428], "alive": [1], "wealth": [0.027], "defense": [0.491]}, "21,21": {"food": [0.743], "pop": [1.973], "alive": [1], "wealth": [0.051], "defense": [0.891]}, "25,19": {"food": [0.793], "pop": [1.66], "alive": [1], "wealth": [0.002], "defense": [0.581]}, "17,27": {"food": [0.803], "pop": [1.514], "alive": [1], "wealth": [0.033], "defense": [0.593]}, "28,16": {"food": [0.86], "pop": [1.074], "alive": [1], "wealth": [0.007], "defense": [0.427]}, "27,29": {"food": [0.928], "pop": [0.554], "alive": [1], "wealth": [0.003], "defense": [0.205]}, "19,26": {"food": [0.901], "pop": [0.763], "alive": [1], "wealth": [0.01], "defense": [0.282]}, "25,25": {"food": [0.924], "pop": [0.583], "alive": [1], "wealth": [0.004], "defense": [0.229]}, "20,20": {"food": [0.924], "pop": [0.582], "alive": [1], "wealth": [0.006], "defense": [0.229]}, "24,24": {"food": [0.927], "pop": [0.563], "alive": [1], "wealth": [0.003], "defense": [0.226]}, "18,21": {"food": [0.92], "pop": [0.613], "alive": [1], "wealth": [0.007], "defense": [0.255]}, "29,24": {"food": [0.919], "pop": [0.62], "alive": [1], "wealth": [0.007], "defense": [0.256]}, "26,20": {"food": [0.917], "pop": [0.637], "alive": [1], "wealth": [0.005], "defense": [0.258]}, "29,16": {"food": [0.918], "pop": [0.628], "alive": [1], "wealth": [0.013], "defense": [0.256]}, "23,27": {"food": [0.94], "pop": [0.46], "alive": [1], "wealth": [0.017], "defense": [0.176]}, "19,21": {"food": [0.928], "pop": [0.554], "alive": [1], "wealth": [0.011], "defense": [0.221]}, "24,28": {"food": [0.865], "pop": [0.527], "alive": [1], "wealth": [0.02], "defense": [0.21]}, "18,29": {"food": [0.527], "pop": [0.419], "alive": [1], "wealth": [0.001], "defense": [0.158]}, "22,21": {"food": [0.343], "pop": [0.272], "alive": [1], "wealth": [0.0], "defense": [0.088]}, "22,12": {"food": [0.176], "pop": [2.436], "alive": [1], "wealth": [0.046], "defense": [1.0]}, "16,12": {"food": [0.796], "pop": [1.717], "alive": [1], "wealth": [0.037], "defense": [0.656]}, "24,3": {"food": [0.809], "pop": [1.61], "alive": [1], "wealth": [0.003], "defense": [0.539]}, "24,11": {"food": [0.822], "pop": [1.502], "alive": [1], "wealth": [0.03], "defense": [0.608]}, "21,11": {"food": [0.894], "pop": [0.891], "alive": [1], "wealth": [0.035], "defense": [0.348]}, "23,4": {"food": [0.856], "pop": [1.21], "alive": [1], "wealth": [0.058], "defense": [0.474]}, "28,14": {"food": [0.864], "pop": [1.15], "alive": [1], "wealth": [0.041], "defense": [0.45]}, "24,5": {"food": [0.907], "pop": [0.784], "alive": [1], "wealth": [0.044], "defense": [0.313]}, "23,12": {"food": [0.91], "pop": [0.755], "alive": [1], "wealth": [0.007], "defense": [0.311]}, "17,10": {"food": [0.936], "pop": [0.538], "alive": [1], "wealth": [0.027], "defense": [0.215]}, "25,5": {"food": [0.926], "pop": [0.628], "alive": [1], "wealth": [0.038], "defense": [0.256]}, "29,14": {"food": [0.682], "pop": [0.444], "alive": [1], "wealth": [0.002], "defense": [0.183]}, "21,12": {"food": [0.068], "pop": [0.5], "alive": [1], "wealth": [0.011], "defense": [0.2]}, "18,12": {"food": [0.014], "pop": [0.4], "alive": [1], "wealth": [0.001], "defense": [0.15]}, "4,19": {"food": [0.604], "pop": [1.667], "alive": [1], "wealth": [0.035], "defense": [0.65]}, "5,18": {"food": [0.817], "pop": [1.685], "alive": [1], "wealth": [0.045], "defense": [0.744]}, "14,19": {"food": [0.575], "pop": [1.871], "alive": [1], "wealth": [0.012], "defense": [0.657]}, "5,25": {"food": [0.855], "pop": [1.335], "alive": [1], "wealth": [0.0], "defense": [0.454]}, "3,26": {"food": [0.908], "pop": [0.85], "alive": [1], "wealth": [0.0], "defense": [0.348]}, "11,15": {"food": [0.929], "pop": [0.656], "alive": [1], "wealth": [0.002], "defense": [0.263]}, "6,25": {"food": [0.927], "pop": [0.674], "alive": [1], "wealth": [0.0], "defense": [0.281]}, "2,16": {"food": [0.898], "pop": [0.938], "alive": [1], "wealth": [0.008], "defense": [0.292]}, "3,16": {"food": [0.952], "pop": [0.441], "alive": [1], "wealth": [0.001], "defense": [0.175]}, "5,20": {"food": [0.95], "pop": [0.46], "alive": [1], "wealth": [0.005], "defense": [0.176]}, "6,19": {"food": [0.94], "pop": [0.554], "alive": [1], "wealth": [0.01], "defense": [0.222]}, "12,19": {"food": [0.94], "pop": [0.556], "alive": [1], "wealth": [0.003], "defense": [0.222]}, "11,17": {"food": [0.952], "pop": [0.438], "alive": [1], "wealth": [0.0], "defense": [0.167]}, "3,19": {"food": [0.161], "pop": [0.5], "alive": [1], "wealth": [0.008], "defense": [0.2]}, "14,3": {"food": [0.689], "pop": [2.365], "alive": [1], "wealth": [0.045], "defense": [1.0]}, "4,10": {"food": [0.412], "pop": [2.128], "alive": [1], "wealth": [0.077], "defense": [0.968]}, "5,9": {"food": [0.807], "pop": [1.438], "alive": [1], "wealth": [0.012], "defense": [0.593]}, "11,13": {"food": [0.852], "pop": [1.129], "alive": [1], "wealth": [0.0], "defense": [0.454]}, "11,3": {"food": [0.831], "pop": [1.29], "alive": [1], "wealth": [0.005], "defense": [0.45]}, "6,9": {"food": [0.868], "pop": [1.008], "alive": [1], "wealth": [0.001], "defense": [0.421]}, "8,10": {"food": [0.9], "pop": [0.759], "alive": [1], "wealth": [0.0], "defense": [0.309]}, "14,1": {"food": [0.915], "pop": [0.645], "alive": [1], "wealth": [0.012], "defense": [0.268]}, "4,12": {"food": [0.912], "pop": [0.67], "alive": [1], "wealth": [0.02], "defense": [0.271]}, "12,2": {"food": [0.915], "pop": [0.645], "alive": [1], "wealth": [0.01], "defense": [0.268]}, "4,8": {"food": [0.628], "pop": [0.526], "alive": [1], "wealth": [0.018], "defense": [0.22]}, "12,3": {"food": [0.183], "pop": [0.4], "alive": [1], "wealth": [0.001], "defense": [0.15]}, "32,24": {"food": [0.517], "pop": [2.742], "alive": [1], "wealth": [0.055], "defense": [1.0]}, "34,29": {"food": [0.262], "pop": [2.223], "alive": [1], "wealth": [0.041], "defense": [1.0]}, "31,22": {"food": [0.111], "pop": [2.124], "alive": [1], "wealth": [0.037], "defense": [1.0]}, "35,27": {"food": [0.647], "pop": [1.827], "alive": [1], "wealth": [0.046], "defense": [0.791]}, "37,16": {"food": [0.749], "pop": [1.65], "alive": [1], "wealth": [0.043], "defense": [0.721]}, "36,27": {"food": [0.842], "pop": [1.627], "alive": [1], "wealth": [0.038], "defense": [0.66]}, "37,15": {"food": [0.887], "pop": [1.164], "alive": [1], "wealth": [0.005], "defense": [0.478]}, "35,26": {"food": [0.892], "pop": [1.117], "alive": [1], "wealth": [0.048], "defense": [0.45]}, "34,28": {"food": [0.914], "pop": [0.883], "alive": [1], "wealth": [0.036], "defense": [0.361]}, "31,23": {"food": [0.922], "pop": [0.809], "alive": [1], "wealth": [0.007], "defense": [0.328]}, "32,22": {"food": [0.926], "pop": [0.767], "alive": [1], "wealth": [0.013], "defense": [0.312]}, "31,17": {"food": [0.928], "pop": [0.743], "alive": [1], "wealth": [0.016], "defense": [0.298]}, "36,15": {"food": [0.94], "pop": [0.615], "alive": [1], "wealth": [0.011], "defense": [0.255]}, "30,18": {"food": [0.955], "pop": [0.468], "alive": [1], "wealth": [0.023], "defense": [0.174]}, "32,23": {"food": [0.16], "pop": [0.5], "alive": [1], "wealth": [0.01], "defense": [0.22]}, "30,17": {"food": [0.16], "pop": [0.5], "alive": [1], "wealth": [0.012], "defense": [0.2]}, "13,31": {"food": [0.338], "pop": [2.477], "alive": [1], "wealth": [0.041], "defense": [1.0]}, "12,38": {"food": [0.916], "pop": [0.89], "alive": [1], "wealth": [0.386], "defense": [0.262]}, "12,36": {"food": [0.927], "pop": [0.78], "alive": [1], "wealth": [0.035], "defense": [0.29]}, "10,37": {"food": [0.963], "pop": [0.394], "alive": [1], "wealth": [0.003], "defense": [0.145]}, "12,30": {"food": [0.928], "pop": [0.762], "alive": [1], "wealth": [0.012], "defense": [0.312]}, "11,31": {"food": [0.942], "pop": [0.618], "alive": [1], "wealth": [0.011], "defense": [0.255]}, "14,31": {"food": [0.78], "pop": [0.526], "alive": [1], "wealth": [0.032], "defense": [0.21]}, "28,32": {"food": [0.644], "pop": [2.607], "alive": [1], "wealth": [0.147], "defense": [1.0]}, "29,35": {"food": [0.932], "pop": [0.506], "alive": [1], "wealth": [0.005], "defense": [0.037]}, "27,30": {"food": [0.959], "pop": [0.309], "alive": [1], "wealth": [0.003], "defense": [0.108]}, "27,32": {"food": [0.89], "pop": [0.824], "alive": [1], "wealth": [0.037], "defense": [0.332]}, "26,32": {"food": [0.91], "pop": [0.675], "alive": [1], "wealth": [0.035], "defense": [0.271]}, "30,4": {"food": [0.138], "pop": [2.619], "alive": [1], "wealth": [0.025], "defense": [1.0]}, "36,6": {"food": [0.227], "pop": [2.601], "alive": [1], "wealth": [0.018], "defense": [1.0]}, "35,7": {"food": [0.792], "pop": [1.564], "alive": [1], "wealth": [0.013], "defense": [0.79]}, "31,12": {"food": [0.496], "pop": [1.983], "alive": [1], "wealth": [0.037], "defense": [0.853]}, "31,4": {"food": [0.715, 0.637], "pop": [1.405, 1.808], "alive": [1, 1], "wealth": [0.004, 0.005], "defense": [0.565, 0.748]}, "37,7": {"food": [0.828], "pop": [1.35], "alive": [1], "wealth": [0.004], "defense": [0.555]}, "30,5": {"food": [0.842], "pop": [1.24], "alive": [1], "wealth": [0.008], "defense": [0.484]}, "36,14": {"food": [0.891, 0.956], "pop": [0.85, 0.539], "alive": [1, 1], "wealth": [0.007, 0.001], "defense": [0.344, 0.223]}, "37,14": {"food": [0.875], "pop": [0.975], "alive": [1], "wealth": [0.015], "defense": [0.399]}, "30,6": {"food": [0.813], "pop": [0.738], "alive": [1], "wealth": [0.008], "defense": [0.342]}, "36,8": {"food": [0.9], "pop": [0.784], "alive": [1], "wealth": [0.006], "defense": [0.316]}, "32,12": {"food": [0.911], "pop": [0.693], "alive": [1], "wealth": [0.01], "defense": [0.273]}, "31,5": {"food": [0.717], "pop": [0.533], "alive": [1], "wealth": [0.01], "defense": [0.25]}, "38,13": {"food": [0.918], "pop": [0.641], "alive": [1], "wealth": [0.014], "defense": [0.258]}, "34,6": {"food": [0.722], "pop": [0.44], "alive": [1], "wealth": [0.003], "defense": [0.175]}, "30,12": {"food": [0.623, 0.936], "pop": [0.53, 0.789], "alive": [1, 1], "wealth": [0.009, 0.002], "defense": [0.22, 0.316]}, "31,3": {"food": [0.331, 0.176], "pop": [0.5, 0.4], "alive": [1, 1], "wealth": [0.006, 0.0], "defense": [0.21, 0.15]}, "37,33": {"food": [0.865], "pop": [1.284], "alive": [1], "wealth": [0.022], "defense": [0.519]}, "35,31": {"food": [0.859], "pop": [1.344], "alive": [1], "wealth": [0.038], "defense": [0.531]}, "37,31": {"food": [0.904], "pop": [0.907], "alive": [1], "wealth": [0.004], "defense": [0.364]}, "38,32": {"food": [0.914], "pop": [0.812], "alive": [1], "wealth": [0.01], "defense": [0.329]}, "32,36": {"food": [0.921], "pop": [0.751], "alive": [1], "wealth": [0.01], "defense": [0.311]}, "38,30": {"food": [0.938], "pop": [0.586], "alive": [1], "wealth": [0.0], "defense": [0.237]}, "30,37": {"food": [0.935], "pop": [0.613], "alive": [1], "wealth": [0.008], "defense": [0.255]}, "31,34": {"food": [0.942], "pop": [0.551], "alive": [1], "wealth": [0.007], "defense": [0.221]}, "31,36": {"food": [0.736], "pop": [0.419], "alive": [1], "wealth": [0.001], "defense": [0.166]}, "36,30": {"food": [0.954], "pop": [0.438], "alive": [1], "wealth": [0.0], "defense": [0.167]}, "30,14": {"food": [0.664], "pop": [2.173], "alive": [1], "wealth": [0.007], "defense": [0.829]}, "33,2": {"food": [0.879], "pop": [1.477], "alive": [1], "wealth": [0.004], "defense": [0.595]}, "30,3": {"food": [0.875], "pop": [1.533], "alive": [1], "wealth": [0.017], "defense": [0.596]}, "35,9": {"food": [0.885], "pop": [1.414], "alive": [1], "wealth": [0.006], "defense": [0.482]}, "31,2": {"food": [0.941], "pop": [0.729], "alive": [1], "wealth": [0.002], "defense": [0.292]}, "32,3": {"food": [0.944], "pop": [0.681], "alive": [1], "wealth": [0.0], "defense": [0.276]}, "35,14": {"food": [0.945], "pop": [0.679], "alive": [1], "wealth": [0.006], "defense": [0.276]}, "38,7": {"food": [0.925], "pop": [0.924], "alive": [1], "wealth": [0.006], "defense": [0.272]}, "37,6": {"food": [0.947], "pop": [0.648], "alive": [1], "wealth": [0.01], "defense": [0.268]}, "29,13": {"food": [0.727], "pop": [0.53], "alive": [1], "wealth": [0.004], "defense": [0.22]}, "38,6": {"food": [0.349], "pop": [0.4], "alive": [1], "wealth": [0.001], "defense": [0.158]}, "31,6": {"food": [0.174], "pop": [0.5], "alive": [1], "wealth": [0.001], "defense": [0.2]}}, "3": {"17,25": {"food": [0.103], "pop": [2.32], "alive": [1], "wealth": [0.072], "defense": [1.0]}, "20,27": {"food": [0.695], "pop": [2.347], "alive": [1], "wealth": [0.002], "defense": [1.0]}, "21,26": {"food": [0.801], "pop": [1.529], "alive": [1], "wealth": [0.002], "defense": [0.611]}, "18,20": {"food": [0.478], "pop": [1.677], "alive": [1], "wealth": [0.058], "defense": [0.625]}, "15,25": {"food": [0.819], "pop": [1.396], "alive": [1], "wealth": [0.025], "defense": [0.55]}, "17,26": {"food": [0.853], "pop": [1.129], "alive": [1], "wealth": [0.022], "defense": [0.448]}, "18,27": {"food": [0.868], "pop": [1.018], "alive": [1], "wealth": [0.001], "defense": [0.408]}, "21,25": {"food": [0.904], "pop": [0.743], "alive": [1], "wealth": [0.005], "defense": [0.298]}, "18,21": {"food": [0.945], "pop": [0.42], "alive": [1], "wealth": [0.012], "defense": [0.162]}, "29,17": {"food": [0.927], "pop": [0.561], "alive": [1], "wealth": [0.003], "defense": [0.226]}, "22,27": {"food": [0.927], "pop": [0.561], "alive": [1], "wealth": [0.0], "defense": [0.226]}, "20,29": {"food": [0.912], "pop": [0.678], "alive": [1], "wealth": [0.0], "defense": [0.272]}, "29,16": {"food": [0.916], "pop": [0.651], "alive": [1], "wealth": [0.006], "defense": [0.268]}, "18,19": {"food": [0.859], "pop": [0.336], "alive": [1], "wealth": [0.003], "defense": [0.123]}, "21,28": {"food": [0.672], "pop": [0.527], "alive": [1], "wealth": [0.0], "defense": [0.22]}, "21,27": {"food": [0.159], "pop": [0.4], "alive": [1], "wealth": [0.0], "defense": [0.158]}, "19,21": {"food": [0.189], "pop": [0.4], "alive": [1], "wealth": [0.001], "defense": [0.15]}, "14,20": {"food": [0.459], "pop": [1.964], "alive": [1], "wealth": [0.043], "defense": [0.783]}, "13,19": {"food": [0.321], "pop": [1.47], "alive": [1], "wealth": [0.031], "defense": [0.716]}, "13,20": {"food": [0.91], "pop": [0.992], "alive": [1], "wealth": [0.014], "defense": [0.397]}, "13,18": {"food": [0.939], "pop": [0.677], "alive": [1], "wealth": [0.001], "defense": [0.271]}, "5,29": {"food": [0.929], "pop": [0.784], "alive": [1], "wealth": [0.002], "defense": [0.326]}, "6,29": {"food": [0.947], "pop": [0.583], "alive": [1], "wealth": [0.0], "defense": [0.237]}, "14,19": {"food": [0.698], "pop": [0.439], "alive": [1], "wealth": [0.0], "defense": [0.175]}, "13,21": {"food": [0.437], "pop": [0.5], "alive": [1], "wealth": [0.01], "defense": [0.21]}, "14,18": {"food": [0.079], "pop": [0.5], "alive": [1], "wealth": [0.007], "defense": [0.2]}, "24,6": {"food": [0.187], "pop": [2.787], "alive": [1], "wealth": [0.029], "defense": [1.0]}, "15,3": {"food": [0.409], "pop": [2.004], "alive": [1], "wealth": [0.075], "defense": [0.791]}, "15,1": {"food": [0.837], "pop": [1.329], "alive": [1], "wealth": [0.075], "defense": [0.534]}, "23,5": {"food": [0.849], "pop": [1.392], "alive": [1], "wealth": [0.012], "defense": [0.556]}, "25,6": {"food": [0.877], "pop": [1.134], "alive": [1], "wealth": [0.01], "defense": [0.453]}, "20,14": {"food": [0.891], "pop": [1.012], "alive": [1], "wealth": [0.008], "defense": [0.407]}, "26,6": {"food": [0.927], "pop": [0.672], "alive": [1], "wealth": [0.001], "defense": [0.267]}, "23,7": {"food": [0.936], "pop": [0.59], "alive": [1], "wealth": [0.004], "defense": [0.238]}, "24,7": {"food": [0.922], "pop": [0.725], "alive": [1], "wealth": [0.008], "defense": [0.297]}, "15,2": {"food": [0.939], "pop": [0.564], "alive": [1], "wealth": [0.009], "defense": [0.226]}, "16,3": {"food": [0.557], "pop": [0.527], "alive": [1], "wealth": [0.017], "defense": [0.21]}, "13,14": {"food": [0.828, 0.937], "pop": [1.697, 0.647], "alive": [1, 1], "wealth": [0.02, 0.006], "defense": [0.673, 0.258]}, "10,5": {"food": [0.603, 0.896], "pop": [1.815, 1.056], "alive": [1, 1], "wealth": [0.072, 0.013], "defense": [0.69, 0.417]}, "7,2": {"food": [0.609], "pop": [1.711], "alive": [1], "wealth": [0.043], "defense": [0.629]}, "6,2": {"food": [0.918, 0.957], "pop": [0.81, 0.442], "alive": [1, 1], "wealth": [0.005, 0.01], "defense": [0.324, 0.175]}, "5,2": {"food": [0.899], "pop": [0.995], "alive": [1], "wealth": [0.036], "defense": [0.398]}, "3,1": {"food": [0.916], "pop": [0.829], "alive": [1], "wealth": [0.031], "defense": [0.33]}, "4,1": {"food": [0.773], "pop": [0.569], "alive": [1], "wealth": [0.027], "defense": [0.262]}, "5,3": {"food": [0.948, 0.904], "pop": [0.514, 0.977], "alive": [1, 1], "wealth": [0.003, 0.056], "defense": [0.204, 0.385]}, "12,5": {"food": [0.579], "pop": [0.423], "alive": [1], "wealth": [0.007], "defense": [0.154]}, "13,12": {"food": [0.647], "pop": [0.42], "alive": [1], "wealth": [0.002], "defense": [0.166]}, "7,1": {"food": [0.412, 0.073], "pop": [0.5, 0.5], "alive": [1, 1], "wealth": [0.01, 0.019], "defense": [0.21, 0.2]}, "11,5": {"food": [0.23], "pop": [0.4], "alive": [1], "wealth": [0.002], "defense": [0.158]}, "16,38": {"food": [0.933], "pop": [0.562], "alive": [1], "wealth": [0.135], "defense": [0.182]}, "16,37": {"food": [0.983], "pop": [0.141], "alive": [1], "wealth": [0.012], "defense": [0.052]}, "35,23": {"food": [0.22], "pop": [2.544], "alive": [1], "wealth": [0.052], "defense": [1.0]}, "30,16": {"food": [0.392], "pop": [2.287], "alive": [1], "wealth": [0.039], "defense": [1.0]}, "31,18": {"food": [0.821], "pop": [1.526], "alive": [1], "wealth": [0.007], "defense": [0.61]}, "31,15": {"food": [0.872], "pop": [1.091], "alive": [1], "wealth": [0.001], "defense": [0.443]}, "30,27": {"food": [0.843], "pop": [1.418], "alive": [1], "wealth": [0.006], "defense": [0.504]}, "34,22": {"food": [0.914], "pop": [0.735], "alive": [1], "wealth": [0.008], "defense": [0.295]}, "31,27": {"food": [0.925], "pop": [0.639], "alive": [1], "wealth": [0.002], "defense": [0.217]}, "36,24": {"food": [0.083], "pop": [0.5], "alive": [1], "wealth": [0.012], "defense": [0.2]}, "2,31": {"food": [0.042], "pop": [2.248], "alive": [1], "wealth": [0.016], "defense": [1.0]}, "10,30": {"food": [0.526], "pop": [2.057], "alive": [1], "wealth": [0.029], "defense": [0.923]}, "4,32": {"food": [0.812], "pop": [1.702], "alive": [1], "wealth": [0.016], "defense": [0.676]}, "13,33": {"food": [0.802], "pop": [1.626], "alive": [1], "wealth": [0.005], "defense": [0.659]}, "3,32": {"food": [0.899], "pop": [0.909], "alive": [1], "wealth": [0.002], "defense": [0.372]}, "2,32": {"food": [0.921], "pop": [0.712], "alive": [1], "wealth": [0.002], "defense": [0.29]}, "3,34": {"food": [0.927], "pop": [0.662], "alive": [1], "wealth": [0.0], "defense": [0.266]}, "9,30": {"food": [0.923], "pop": [0.694], "alive": [1], "wealth": [0.008], "defense": [0.273]}, "1,31": {"food": [0.949], "pop": [0.457], "alive": [1], "wealth": [0.0], "defense": [0.176]}, "10,31": {"food": [0.953], "pop": [0.423], "alive": [1], "wealth": [0.005], "defense": [0.156]}, "12,33": {"food": [0.525], "pop": [0.421], "alive": [1], "wealth": [0.003], "defense": [0.147]}, "33,3": {"food": [0.165], "pop": [2.272], "alive": [1], "wealth": [0.013], "defense": [1.0]}, "33,5": {"food": [0.6], "pop": [2.266], "alive": [1], "wealth": [0.013], "defense": [1.0]}, "32,4": {"food": [0.592], "pop": [1.329], "alive": [1], "wealth": [0.003], "defense": [0.625]}, "33,4": {"food": [0.518], "pop": [1.262], "alive": [1], "wealth": [0.003], "defense": [0.518]}, "31,3": {"food": [0.828], "pop": [1.188], "alive": [1], "wealth": [0.005], "defense": [0.476]}, "33,1": {"food": [0.864], "pop": [0.937], "alive": [1], "wealth": [0.004], "defense": [0.381]}, "34,2": {"food": [0.89], "pop": [0.762], "alive": [1], "wealth": [0.003], "defense": [0.312]}, "35,5": {"food": [0.933], "pop": [0.461], "alive": [1], "wealth": [0.0], "defense": [0.184]}, "32,14": {"food": [0.915], "pop": [0.589], "alive": [1], "wealth": [0.012], "defense": [0.233]}, "34,6": {"food": [0.92], "pop": [0.554], "alive": [1], "wealth": [0.003], "defense": [0.221]}, "34,4": {"food": [0.143], "pop": [0.5], "alive": [1], "wealth": [0.001], "defense": [0.2]}, "6,1": {"food": [0.223], "pop": [2.271], "alive": [1], "wealth": [0.083], "defense": [0.941]}, "4,2": {"food": [0.658], "pop": [1.29], "alive": [1], "wealth": [0.058], "defense": [0.581]}, "12,13": {"food": [0.853], "pop": [1.501], "alive": [1], "wealth": [0.009], "defense": [0.483]}, "11,4": {"food": [0.913], "pop": [0.889], "alive": [1], "wealth": [0.002], "defense": [0.361]}, "14,14": {"food": [0.903], "pop": [0.862], "alive": [1], "wealth": [0.001], "defense": [0.354]}, "6,14": {"food": [0.9], "pop": [1.019], "alive": [1], "wealth": [0.02], "defense": [0.408]}, "5,1": {"food": [0.166], "pop": [0.5], "alive": [1], "wealth": [0.013], "defense": [0.2]}}, "4": {"26,24": {"food": [0.54], "pop": [2.238], "alive": [1], "wealth": [0.003], "defense": [0.943]}, "20,28": {"food": [0.373], "pop": [1.993], "alive": [1], "wealth": [0.042], "defense": [1.0]}, "27,25": {"food": [0.663], "pop": [1.744], "alive": [1], "wealth": [0.025], "defense": [0.86]}, "27,18": {"food": [0.029], "pop": [2.447], "alive": [1], "wealth": [0.048], "defense": [0.938]}, "25,24": {"food": [0.833], "pop": [1.526], "alive": [1], "wealth": [0.003], "defense": [0.61]}, "27,17": {"food": [0.616], "pop": [1.499], "alive": [1], "wealth": [0.049], "defense": [0.602]}, "15,20": {"food": [0.894], "pop": [0.969], "alive": [1], "wealth": [0.013], "defense": [0.384]}, "21,28": {"food": [0.98], "pop": [0.185], "alive": [1], "wealth": [0.001], "defense": [0.058]}, "28,24": {"food": [0.911], "pop": [0.815], "alive": [1], "wealth": [0.007], "defense": [0.319]}, "27,23": {"food": [0.918], "pop": [0.75], "alive": [1], "wealth": [0.001], "defense": [0.301]}, "26,18": {"food": [0.946], "pop": [0.491], "alive": [1], "wealth": [0.008], "defense": [0.19]}, "28,26": {"food": [0.931], "pop": [0.628], "alive": [1], "wealth": [0.006], "defense": [0.256]}, "17,15": {"food": [0.947], "pop": [0.485], "alive": [1], "wealth": [0.0], "defense": [0.194]}, "15,19": {"food": [0.957], "pop": [0.394], "alive": [1], "wealth": [0.004], "defense": [0.156]}, "16,15": {"food": [0.949], "pop": [0.463], "alive": [1], "wealth": [0.0], "defense": [0.192]}, "20,27": {"food": [0.933], "pop": [0.609], "alive": [1], "wealth": [0.011], "defense": [0.245]}, "26,17": {"food": [0.949], "pop": [0.462], "alive": [1], "wealth": [0.001], "defense": [0.184]}, "26,22": {"food": [0.16], "pop": [0.5], "alive": [1], "wealth": [0.001], "defense": [0.2]}, "18,28": {"food": [0.107], "pop": [0.5], "alive": [1], "wealth": [0.01], "defense": [0.2]}, "28,25": {"food": [0.108], "pop": [0.4], "alive": [1], "wealth": [0.0], "defense": [0.15]}, "27,16": {"food": [0.006], "pop": [0.4], "alive": [1], "wealth": [0.005], "defense": [0.15]}, "27,26": {"food": [0.186], "pop": [0.4], "alive": [1], "wealth": [0.001], "defense": [0.15]}, "17,6": {"food": [0.641], "pop": [2.83], "alive": [1], "wealth": [0.073], "defense": [1.0]}, "27,4": {"food": [0.008], "pop": [3.127], "alive": [1], "wealth": [0.049], "defense": [1.0]}, "19,9": {"food": [0.695, 0.26], "pop": [1.983, 0.5], "alive": [1, 1], "wealth": [0.075, 0.018], "defense": [0.79, 0.21]}, "22,14": {"food": [0.802], "pop": [1.537], "alive": [1], "wealth": [0.07], "defense": [0.615]}, "20,9": {"food": [0.868, 0.839], "pop": [1.029, 1.463], "alive": [1, 1], "wealth": [0.024, 0.009], "defense": [0.416, 0.592]}, "20,11": {"food": [0.864, 0.533], "pop": [1.058, 2.709], "alive": [1, 1], "wealth": [0.011, 0.035], "defense": [0.425, 1.0]}, "27,2": {"food": [0.867], "pop": [1.031], "alive": [1], "wealth": [0.017], "defense": [0.41]}, "26,4": {"food": [0.892], "pop": [0.839], "alive": [1], "wealth": [0.015], "defense": [0.334]}, "15,6": {"food": [0.931, 0.16], "pop": [0.534, 0.5], "alive": [1, 1], "wealth": [0.008, 0.017], "defense": [0.207, 0.2]}, "29,4": {"food": [0.762], "pop": [0.293], "alive": [1], "wealth": [0.0], "defense": [0.092]}, "28,5": {"food": [0.941], "pop": [0.461], "alive": [1], "wealth": [0.0], "defense": [0.184]}, "16,12": {"food": [0.938], "pop": [0.48], "alive": [1], "wealth": [0.003], "defense": [0.186]}, "28,3": {"food": [0.836], "pop": [0.528], "alive": [1], "wealth": [0.011], "defense": [0.22]}, "19,10": {"food": [0.508], "pop": [0.527], "alive": [1], "wealth": [0.017], "defense": [0.21]}, "15,14": {"food": [0.351, 0.986], "pop": [0.5, 0.132], "alive": [1, 1], "wealth": [0.009, 0.001], "defense": [0.2, 0.035]}, "13,21": {"food": [0.558], "pop": [2.16], "alive": [1], "wealth": [0.005], "defense": [0.913]}, "13,22": {"food": [0.595], "pop": [2.038], "alive": [1], "wealth": [0.038], "defense": [0.997]}, "10,21": {"food": [0.568], "pop": [1.434], "alive": [1], "wealth": [0.001], "defense": [0.74]}, "4,15": {"food": [0.865], "pop": [1.45], "alive": [1], "wealth": [0.002], "defense": [0.671]}, "2,15": {"food": [0.925], "pop": [0.799], "alive": [1], "wealth": [0.0], "defense": [0.325]}, "12,17": {"food": [0.922], "pop": [0.831], "alive": [1], "wealth": [0.005], "defense": [0.33]}, "14,17": {"food": [0.951], "pop": [0.527], "alive": [1], "wealth": [0.011], "defense": [0.192]}, "14,23": {"food": [0.928], "pop": [0.769], "alive": [1], "wealth": [0.012], "defense": [0.302]}, "14,19": {"food": [0.951], "pop": [0.528], "alive": [1], "wealth": [0.0], "defense": [0.206]}, "11,21": {"food": [0.942], "pop": [0.617], "alive": [1], "wealth": [0.001], "defense": [0.255]}, "3,16": {"food": [0.941], "pop": [0.635], "alive": [1], "wealth": [0.001], "defense": [0.258]}, "11,22": {"food": [0.942], "pop": [0.621], "alive": [1], "wealth": [0.01], "defense": [0.246]}, "9,21": {"food": [0.946], "pop": [0.582], "alive": [1], "wealth": [0.0], "defense": [0.243]}, "13,19": {"food": [0.393], "pop": [0.5], "alive": [1], "wealth": [0.001], "defense": [0.21]}, "3,15": {"food": [0.163], "pop": [0.5], "alive": [1], "wealth": [0.0], "defense": [0.21]}, "14,21": {"food": [0.168], "pop": [0.5], "alive": [1], "wealth": [0.009], "defense": [0.2]}, "9,22": {"food": [0.146], "pop": [0.5], "alive": [1], "wealth": [0.0], "defense": [0.2]}, "2,1": {"food": [0.799], "pop": [1.506], "alive": [1], "wealth": [0.014], "defense": [0.433]}, "1,3": {"food": [0.88], "pop": [0.844], "alive": [1], "wealth": [0.009], "defense": [0.344]}, "14,2": {"food": [0.907], "pop": [0.649], "alive": [1], "wealth": [0.0], "defense": [0.263]}, "14,5": {"food": [0.904], "pop": [0.67], "alive": [1], "wealth": [0.002], "defense": [0.267]}, "11,12": {"food": [0.886], "pop": [0.8], "alive": [1], "wealth": [0.016], "defense": [0.267]}, "6,4": {"food": [0.843], "pop": [1.1], "alive": [1], "wealth": [0.004], "defense": [0.333]}, "2,4": {"food": [0.902], "pop": [0.686], "alive": [1], "wealth": [0.008], "defense": [0.282]}, "11,14": {"food": [0.625], "pop": [0.418], "alive": [1], "wealth": [0.002], "defense": [0.158]}, "6,3": {"food": [0.169], "pop": [0.4], "alive": [1], "wealth": [0.0], "defense": [0.15]}, "1,2": {"food": [0.176], "pop": [0.4], "alive": [1], "wealth": [0.001], "defense": [0.15]}, "12,14": {"food": [0.125], "pop": [0.4], "alive": [1], "wealth": [0.0], "defense": [0.15]}, "23,33": {"food": [0.084], "pop": [3.224], "alive": [1], "wealth": [0.034], "defense": [1.0]}, "19,30": {"food": [0.917], "pop": [0.943], "alive": [1], "wealth": [0.087], "defense": [0.272]}, "16,34": {"food": [0.874], "pop": [1.433], "alive": [1], "wealth": [0.004], "defense": [0.574]}, "24,34": {"food": [0.867], "pop": [1.517], "alive": [1], "wealth": [0.014], "defense": [0.594]}, "16,33": {"food": [0.895], "pop": [1.194], "alive": [1], "wealth": [0.009], "defense": [0.472]}, "25,33": {"food": [0.892], "pop": [1.23], "alive": [1], "wealth": [0.012], "defense": [0.482]}, "16,32": {"food": [0.77], "pop": [0.341], "alive": [1], "wealth": [0.003], "defense": [0.106]}, "23,35": {"food": [0.929], "pop": [0.807], "alive": [1], "wealth": [0.009], "defense": [0.318]}, "22,32": {"food": [0.945], "pop": [0.625], "alive": [1], "wealth": [0.008], "defense": [0.256]}, "23,32": {"food": [0.555], "pop": [0.422], "alive": [1], "wealth": [0.003], "defense": [0.182]}, "24,32": {"food": [0.959], "pop": [0.461], "alive": [1], "wealth": [0.001], "defense": [0.176]}, "17,34": {"food": [0.867], "pop": [0.527], "alive": [1], "wealth": [0.001], "defense": [0.22]}, "30,10": {"food": [0.202], "pop": [2.216], "alive": [1], "wealth": [0.023], "defense": [1.0]}, "35,14": {"food": [0.644], "pop": [1.885], "alive": [1], "wealth": [0.003], "defense": [0.76]}, "37,12": {"food": [0.873], "pop": [1.692], "alive": [1], "wealth": [0.01], "defense": [0.746]}, "34,4": {"food": [0.741], "pop": [1.684], "alive": [1], "wealth": [0.011], "defense": [0.645]}, "30,8": {"food": [0.907], "pop": [1.241], "alive": [1], "wealth": [0.009], "defense": [0.51]}, "34,3": {"food": [0.928], "pop": [0.956], "alive": [1], "wealth": [0.009], "defense": [0.391]}, "34,5": {"food": [0.952], "pop": [0.642], "alive": [1], "wealth": [0.001], "defense": [0.262]}, "37,13": {"food": [0.939], "pop": [0.808], "alive": [1], "wealth": [0.008], "defense": [0.328]}, "30,12": {"food": [0.947], "pop": [0.705], "alive": [1], "wealth": [0.006], "defense": [0.285]}, "34,6": {"food": [0.959], "pop": [0.548], "alive": [1], "wealth": [0.0], "defense": [0.217]}, "35,3": {"food": [0.967], "pop": [0.439], "alive": [1], "wealth": [0.001], "defense": [0.175]}, "31,9": {"food": [0.926], "pop": [0.526], "alive": [1], "wealth": [0.005], "defense": [0.22]}, "38,14": {"food": [0.398], "pop": [0.5], "alive": [1], "wealth": [0.006], "defense": [0.22]}, "35,12": {"food": [0.958], "pop": [0.554], "alive": [1], "wealth": [0.002], "defense": [0.222]}, "33,5": {"food": [0.19], "pop": [0.4], "alive": [1], "wealth": [0.0], "defense": [0.15]}, "34,28": {"food": [0.164], "pop": [2.182], "alive": [1], "wealth": [0.022], "defense": [1.0]}, "37,20": {"food": [0.63], "pop": [2.031], "alive": [1], "wealth": [0.034], "defense": [1.0]}, "35,28": {"food": [0.883], "pop": [1.459], "alive": [1], "wealth": [0.014], "defense": [0.591]}, "36,29": {"food": [0.891], "pop": [1.355], "alive": [1], "wealth": [0.004], "defense": [0.547]}, "34,23": {"food": [0.869], "pop": [1.634], "alive": [1], "wealth": [0.012], "defense": [0.581]}, "35,15": {"food": [0.924], "pop": [0.943], "alive": [1], "wealth": [0.008], "defense": [0.335]}, "33,15": {"food": [0.92], "pop": [0.996], "alive": [1], "wealth": [0.018], "defense": [0.402]}, "34,15": {"food": [0.947], "pop": [0.655], "alive": [1], "wealth": [0.001], "defense": [0.271]}, "36,21": {"food": [0.947], "pop": [0.66], "alive": [1], "wealth": [0.005], "defense": [0.272]}, "34,29": {"food": [0.947], "pop": [0.655], "alive": [1], "wealth": [0.003], "defense": [0.263]}, "37,18": {"food": [0.935], "pop": [0.815], "alive": [1], "wealth": [0.01], "defense": [0.321]}, "36,19": {"food": [0.95], "pop": [0.618], "alive": [1], "wealth": [0.009], "defense": [0.255]}, "35,23": {"food": [0.821], "pop": [0.444], "alive": [1], "wealth": [0.001], "defense": [0.191]}, "34,27": {"food": [0.783], "pop": [0.211], "alive": [1], "wealth": [0.0], "defense": [0.063]}, "34,22": {"food": [0.955], "pop": [0.556], "alive": [1], "wealth": [0.003], "defense": [0.232]}, "36,20": {"food": [0.347], "pop": [0.5], "alive": [1], "wealth": [0.008], "defense": [0.21]}, "8,34": {"food": [0.746], "pop": [1.629], "alive": [1], "wealth": [0.003], "defense": [0.606]}, "7,32": {"food": [0.658], "pop": [1.603], "alive": [1], "wealth": [0.006], "defense": [0.725]}, "9,33": {"food": [0.907], "pop": [1.206], "alive": [1], "wealth": [0.0], "defense": [0.499]}, "7,34": {"food": [0.887], "pop": [1.469], "alive": [1], "wealth": [0.006], "defense": [0.596]}, "12,30": {"food": [0.923], "pop": [0.996], "alive": [1], "wealth": [0.063], "defense": [0.405]}, "5,33": {"food": [0.922], "pop": [1.01], "alive": [1], "wealth": [0.005], "defense": [0.407]}, "13,37": {"food": [0.959], "pop": [0.533], "alive": [1], "wealth": [0.003], "defense": [0.207]}, "14,35": {"food": [0.707], "pop": [0.531], "alive": [1], "wealth": [0.006], "defense": [0.23]}, "13,35": {"food": [0.964], "pop": [0.461], "alive": [1], "wealth": [0.003], "defense": [0.176]}, "13,36": {"food": [0.308], "pop": [0.5], "alive": [1], "wealth": [0.005], "defense": [0.21]}, "5,32": {"food": [0.176], "pop": [0.5], "alive": [1], "wealth": [0.001], "defense": [0.2]}, "8,35": {"food": [0.149], "pop": [0.4], "alive": [1], "wealth": [0.0], "defense": [0.15]}, "12,13": {"food": [0.406], "pop": [2.736], "alive": [1], "wealth": [0.372], "defense": [1.0]}, "14,7": {"food": [0.54], "pop": [2.227], "alive": [1], "wealth": [0.072], "defense": [1.0]}, "17,9": {"food": [0.583], "pop": [1.837], "alive": [1], "wealth": [0.117], "defense": [0.941]}, "21,9": {"food": [0.415], "pop": [2.02], "alive": [1], "wealth": [0.035], "defense": [0.928]}, "18,9": {"food": [0.827], "pop": [1.57], "alive": [1], "wealth": [0.081], "defense": [0.718]}, "18,8": {"food": [0.922], "pop": [0.714], "alive": [1], "wealth": [0.018], "defense": [0.281]}, "20,6": {"food": [0.893], "pop": [0.973], "alive": [1], "wealth": [0.024], "defense": [0.399]}, "12,12": {"food": [0.916], "pop": [0.763], "alive": [1], "wealth": [0.044], "defense": [0.31]}, "21,8": {"food": [0.913], "pop": [0.794], "alive": [1], "wealth": [0.021], "defense": [0.327]}, "7,14": {"food": [0.948], "pop": [0.475], "alive": [1], "wealth": [0.009], "defense": [0.168]}, "21,11": {"food": [0.958], "pop": [0.382], "alive": [1], "wealth": [0.004], "defense": [0.135]}, "19,8": {"food": [0.932], "pop": [0.62], "alive": [1], "wealth": [0.018], "defense": [0.266]}, "18,11": {"food": [0.936], "pop": [0.586], "alive": [1], "wealth": [0.01], "defense": [0.233]}, "17,7": {"food": [0.168], "pop": [0.425], "alive": [1], "wealth": [0.027], "defense": [0.16]}, "14,9": {"food": [0.117], "pop": [0.4], "alive": [1], "wealth": [0.012], "defense": [0.15]}, "16,8": {"food": [0.032], "pop": [0.4], "alive": [1], "wealth": [0.002], "defense": [0.15]}}}}